crypto_wallet/__init__.py
crypto_wallet/_resources.py
crypto_wallet/exceptions.py
crypto_wallet/wallet.py
mycryptowallet_deskent-0.0.17.data/scripts/wallet.py
mycryptowallet_deskent-0.0.17.dist-info/LICENSE.txt
mycryptowallet_deskent-0.0.17.dist-info/METADATA
mycryptowallet_deskent-0.0.17.dist-info/WHEEL
mycryptowallet_deskent-0.0.17.dist-info/top_level.txt
mycryptowallet_deskent-0.0.17.dist-info/RECORD
