Metadata-Version: 2.1
Name: mycryptowallet-deskent
Version: 0.0.17
Summary: My Crypto Wallet library
Home-page: https://github.com/Deskent/my_cryptowallet
Author: Deskent
Author-email: battenetciz@gmail.com
Classifier: License :: OSI Approved :: MIT License
Classifier: Programming Language :: Python
Classifier: Programming Language :: Python :: 3
Classifier: Programming Language :: Python :: 3 :: Only
Classifier: Programming Language :: Python :: 3.7
Classifier: Programming Language :: Python :: 3.8
Classifier: Programming Language :: Python :: 3.9
Classifier: Programming Language :: Python :: 3.10
Classifier: Operating System :: OS Independent
Requires-Python: >=3.7
License-File: LICENSE.txt
Requires-Dist: bitcoinlib (==0.6.4)
Requires-Dist: myloguru-deskent (==0.0.12)
